sepyrate/__init__.py
sepyrate/sepyrate.py
sepyrate-0.1.0.dist-info/LICENSE.txt
sepyrate-0.1.0.dist-info/METADATA
sepyrate-0.1.0.dist-info/WHEEL
sepyrate-0.1.0.dist-info/top_level.txt
sepyrate-0.1.0.dist-info/RECORD
