Metadata-Version: 2.1
Name: sepyrate
Version: 0.1.0
Summary: A library to display digits into groups of thousands and decimal using various delimiters. 
Author-email: "Vivi Andasari, PhD" <vandasari@gmail.com>
Project-URL: Homepage, https://github.com/vandasari/sepyrate
Project-URL: Repository, https://github.com/vandasari/sepyrate
Project-URL: Issues, https://github.com/vandasari/sepyrate/issues
Keywords: digit grouping,decimal separator,thousands separator
Classifier: Programming Language :: Python :: 3
Classifier: License :: OSI Approved :: MIT License
Classifier: Operating System :: OS Independent
Requires-Python: >=3.9
License-File: LICENSE.txt
